Workbook

Sheet Dashboard
A1: Professional Bookkeeping Workbook
A2: Business / Account | B2: LUXE TRADING MARKETS (PTY) LTD - Gold Business Account 63130993777
A3: Statements processed | B3: 6
A4: Transactions extracted | B4: 2652
A5: Date range | B5: 2025-01-31 to 2025-08-31
A6: Total money in | B6: =SUM(Transactions!M:M) -> 4087898.4
A7: Total money out | B7: =SUM(Transactions!L:L) -> 4036146.7
A8: Net movement | B8: =B6-B7 -> 51751.69
A9: Transactions flagged for review | B9: =COUNTIF(Transactions!R:R,"Review") -> 16
A10: VAT extracted on bank charges | B10: =SUM(Transactions!Q:Q) -> 239.87
A12: Top Categories | B12: Net
A13: Bank Charges | B13: =SUMIFS(Transactions!N:N,Transactions!I:I,A13) -> -1839
A14: Card / Payment Gateway Receipts | B14: =SUMIFS(Transactions!N:N,Transactions!I:I,A14) -> 886200.57
A15: Customer Receipts | B15: =SUMIFS(Transactions!N:N,Transactions!I:I,A15) -> 2496071.6
A16: Internal Transfers | B16: =SUMIFS(Transactions!N:N,Transactions!I:I,A16) -> -226000
A17: International Payments | B17: =SUMIFS(Transactions!N:N,Transactions!I:I,A17) -> -51438.74
A18: Online Payments | B18: =SUMIFS(Transactions!N:N,Transactions!I:I,A18) -> -100
A19: Other Income | B19: =SUMIFS(Transactions!N:N,Transactions!I:I,A19) -> 235626.18
A20: Other Payments | B20: =SUMIFS(Transactions!N:N,Transactions!I:I,A20) -> -175
A21: Supplier / Payout Payments | B21: =SUMIFS(Transactions!N:N,Transactions!I:I,A21) -> -3286593.9

Sheet Transactions
A1: Txn ID | B1: Date | C1: Month | D1: Statement No | E1: Source File | F1: Page | G1: Description | H1: Counterparty Code | I1: Category | J1: GL Account | K1: Type | L1: Debit | M1: Credit | N1: Net Amount | O1: Running Balance | P1: VAT Rate | Q1: VAT Amount | R1: Review Flag | S1: Accountant Notes
A2: 1 | B2: 45688 | C2: 2025-01 | D2: 2 | E2: GOLD_BUSINESS_ACCOUNT_2.pdf | F2: 1 | G2: AccountFee | I2: Bank Charges | J2: Bank Fees | K2: Debit | L2: 89 | M2: 0 | N2: -89 | O2: 839.82 | P2: 0.15 | Q2: 11.61
A3: 2 | B3: 45691 | C3: 2025-02 | D3: 3 | E3: GOLD_BUSINESS_ACCOUNT_3.pdf | F3: 1 | G3: Int-BankingPmtFrmCu32 | H3: Cu32 | I3: Customer Receipts | J3: Sales Income | K3: Credit | L3: 0 | M3: 10 | N3: 10 | O3: 849.82 | P3: 0 | Q3: 0
A4: 3 | B4: 45695 | C4: 2025-02 | D4: 3 | E4: GOLD_BUSINESS_ACCOUNT_3.pdf | F4: 1 | G4: Int-BankingPmtFrmCu10038 | H4: Cu10038 | I4: Customer Receipts | J4: Sales Income | K4: Credit | L4: 0 | M4: 10 | N4: 10 | O4: 859.82 | P4: 0 | Q4: 0
A5: 4 | B5: 45695 | C5: 2025-02 | D5: 3 | E5: GOLD_BUSINESS_ACCOUNT_3.pdf | F5: 1 | G5: Int-BankingPmtFrmCu10106 | H5: Cu10106 | I5: Customer Receipts | J5: Sales Income | K5: Credit | L5: 0 | M5: 10 | N5: 10 | O5: 869.82 | P5: 0 | Q5: 0
A6: 5 | B6: 45698 | C6: 2025-02 | D6: 3 | E6: GOLD_BUSINESS_ACCOUNT_3.pdf | F6: 1 | G6: Int-BankingPmtFrmCu10122 | H6: Cu10122 | I6: Customer Receipts | J6: Sales Income | K6: Credit | L6: 0 | M6: 10 | N6: 10 | O6: 879.82 | P6: 0 | Q6: 0
A7: 6 | B7: 45700 | C7: 2025-02 | D7: 3 | E7: GOLD_BUSINESS_ACCOUNT_3.pdf | F7: 1 | G7: Int-BankingPmtFrmCu10256 | H7: Cu10256 | I7: Customer Receipts | J7: Sales Income | K7: Credit | L7: 0 | M7: 50 | N7: 50 | O7: 929.82 | P7: 0 | Q7: 0
A8: 7 | B8: 45700 | C8: 2025-02 | D8: 3 | E8: GOLD_BUSINESS_ACCOUNT_3.pdf | F8: 1 | G8: Int-BankingPmtFrmCu10256 | H8: Cu10256 | I8: Customer Receipts | J8: Sales Income | K8: Credit | L8: 0 | M8: 20 | N8: 20 | O8: 949.82 | P8: 0 | Q8: 0
A9: 8 | B9: 45700 | C9: 2025-02 | D9: 3 | E9: GOLD_BUSINESS_ACCOUNT_3.pdf | F9: 1 | G9: Int-BankingPmtFrmCu10256 | H9: Cu10256 | I9: Customer Receipts | J9: Sales Income | K9: Credit | L9: 0 | M9: 100 | N9: 100 | O9: 1049.82 | P9: 0 | Q9: 0
A10: 9 | B10: 45700 | C10: 2025-02 | D10: 3 | E10: GOLD_BUSINESS_ACCOUNT_3.pdf | F10: 1 | G10: Int-BankingPmtFrmCu10265 | H10: Cu10265 | I10: Customer Receipts | J10: Sales Income | K10: Credit | L10: 0 | M10: 5000 | N10: 5000 | O10: 6049.82 | P10: 0 | Q10: 0
A11: 10 | B11: 45700 | C11: 2025-02 | D11: 3 | E11: GOLD_BUSINESS_ACCOUNT_3.pdf | F11: 1 | G11: FNBOBTrfFNBOBTrfInv12/02/2025 | I11: Internal Transfers | J11: Transfers | K11: Credit | L11: 0 | M11: 100000 | N11: 100000 | O11: 106049.82 | P11: 0 | Q11: 0
A12: 11 | B12: 45700 | C12: 2025-02 | D12: 3 | E12: GOLD_BUSINESS_ACCOUNT_3.pdf | F12: 1 | G12: FNBOBPmtFNBOB000000002Cu1 Cu1029254 | H12: Cu1 | I12: Supplier / Payout Payments | J12: Cost of Sales / Supplier Payments | K12: Debit | L12: 33597.72 | M12: 0 | N12: -33597.72 | O12: 72452.1 | P12: 0 | Q12: 0
A13: 12 | B13: 45700 | C13: 2025-02 | D13: 3 | E13: GOLD_BUSINESS_ACCOUNT_3.pdf | F13: 1 | G13: FNBOBPmtFNBOB000000001Cu1 Cu1020733 | H13: Cu1 | I13: Supplier / Payout Payments | J13: Cost of Sales / Supplier Payments | K13: Debit | L13: 137.51 | M13: 0 | N13: -137.51 | O13: 72314.59 | P13: 0 | Q13: 0
A14: 13 | B14: 45701 | C14: 2025-02 | D14: 3 | E14: GOLD_BUSINESS_ACCOUNT_3.pdf | F14: 1 | G14: Int-BankingPmtFrmCu10348 | H14: Cu10348 | I14: Customer Receipts | J14: Sales Income | K14: Credit | L14: 0 | M14: 2000 | N14: 2000 | O14: 74314.59 | P14: 0 | Q14: 0
A15: 14 | B15: 45701 | C15: 2025-02 | D15: 3 | E15: GOLD_BUSINESS_ACCOUNT_3.pdf | F15: 1 | G15: Int-BankingPmtFrmCu10473 | H15: Cu10473 | I15: Customer Receipts | J15: Sales Income | K15: Credit | L15: 0 | M15: 3000 | N15: 3000 | O15: 77314.59 | P15: 0 | Q15: 0
A16: 15 | B16: 45701 | C16: 2025-02 | D16: 3 | E16: GOLD_BUSINESS_ACCOUNT_3.pdf | F16: 1 | G16: Int-BankingPmtFrmCu10348 | H16: Cu10348 | I16: Customer Receipts | J16: Sales Income | K16: Credit | L16: 0 | M16: 3000 | N16: 3000 | O16: 80314.59 | P16: 0 | Q16: 0
A17: 16 | B17: 45701 | C17: 2025-02 | D17: 3 | E17: GOLD_BUSINESS_ACCOUNT_3.pdf | F17: 1 | G17: FNBOBPmtFNBOB000000003Cu1 Cu1034868 | H17: Cu1 | I17: Supplier / Payout Payments | J17: Cost of Sales / Supplier Payments | K17: Debit | L17: 3000 | M17: 0 | N17: -3000 | O17: 77314.59 | P17: 0 | Q17: 0
A18: 17 | B18: 45701 | C18: 2025-02 | D18: 3 | E18: GOLD_BUSINESS_ACCOUNT_3.pdf | F18: 1 | G18: Int-BankingPmtFrmCu10283 | H18: Cu10283 | I18: Customer Receipts | J18: Sales Income | K18: Credit | L18: 0 | M18: 10000 | N18: 10000 | O18: 87314.59 | P18: 0 | Q18: 0
A19: 18 | B19: 45701 | C19: 2025-02 | D19: 3 | E19: GOLD_BUSINESS_ACCOUNT_3.pdf | F19: 1 | G19: Int-BankingPmtFrmCu10130 | H19: Cu10130 | I19: Customer Receipts | J19: Sales Income | K19: Credit | L19: 0 | M19: 9000 | N19: 9000 | O19: 96314.59 | P19: 0 | Q19: 0
A20: 19 | B20: 45701 | C20: 2025-02 | D20: 3 | E20: GOLD_BUSINESS_ACCOUNT_3.pdf | F20: 1 | G20: InternetPmtTo11964250498648 808800266000000008 | I20: Online Payments | J20: Online Payments | K20: Debit | L20: 100 | M20: 0 | N20: -100 | O20: 96214.59 | P20: 0 | Q20: 0
A21: 20 | B21: 45701 | C21: 2025-02 | D21: 3 | E21: GOLD_BUSINESS_ACCOUNT_3.pdf | F21: 1 | G21: Int-BankingPmtFrmCu10130 | H21: Cu10130 | I21: Customer Receipts | J21: Sales Income | K21: Credit | L21: 0 | M21: 20000 | N21: 20000 | O21: 116214.59 | P21: 0 | Q21: 0
A22: 21 | B22: 45701 | C22: 2025-02 | D22: 3 | E22: GOLD_BUSINESS_ACCOUNT_3.pdf | F22: 1 | G22: FNBOBPmtFNBOB000000004Cu1 Cu1043269 | H22: Cu1 | I22: Supplier / Payout Payments | J22: Cost of Sales / Supplier Payments | K22: Debit | L22: 209.33 | M22: 0 | N22: -209.33 | O22: 116005.26 | P22: 0 | Q22: 0
A23: 22 | B23: 45701 | C23: 2025-02 | D23: 3 | E23: GOLD_BUSINESS_ACCOUNT_3.pdf | F23: 1 | G23: FNBOBPmtFNBOB000000005Cu1 Cu1016767 | H23: Cu1 | I23: Supplier / Payout Payments | J23: Cost of Sales / Supplier Payments | K23: Debit | L23: 337.84 | M23: 0 | N23: -337.84 | O23: 115667.42 | P23: 0 | Q23: 0
A24: 23 | B24: 45702 | C24: 2025-02 | D24: 3 | E24: GOLD_BUSINESS_ACCOUNT_3.pdf | F24: 1 | G24: Int-BankingPmtFrmCu10369 | H24: Cu10369 | I24: Customer Receipts | J24: Sales Income | K24: Credit | L24: 0 | M24: 100 | N24: 100 | O24: 115767.42 | P24: 0 | Q24: 0
A25: 24 | B25: 45702 | C25: 2025-02 | D25: 3 | E25: GOLD_BUSINESS_ACCOUNT_3.pdf | F25: 1 | G25: FNBOBPmtFNBOB000000006Cu1 Cu1013076 | H25: Cu1 | I25: Supplier / Payout Payments | J25: Cost of Sales / Supplier Payments | K25: Debit | L25: 41334 | M25: 0 | N25: -41334 | O25: 74433.42 | P25: 0 | Q25: 0
A26: 25 | B26: 45702 | C26: 2025-02 | D26: 3 | E26: GOLD_BUSINESS_ACCOUNT_3.pdf | F26: 1 | G26: FNBOBPmtFNBOB000000007Cu1 Cu1047374 | H26: Cu1 | I26: Supplier / Payout Payments | J26: Cost of Sales / Supplier Payments | K26: Debit | L26: 7000 | M26: 0 | N26: -7000 | O26: 67433.42 | P26: 0 | Q26: 0
A27: 26 | B27: 45702 | C27: 2025-02 | D27: 3 | E27: GOLD_BUSINESS_ACCOUNT_3.pdf | F27: 1 | G27: FNBOBPmtFNBOB000000008Cu1 Cu1043273 | H27: Cu1 | I27: Supplier / Payout Payments | J27: Cost of Sales / Supplier Payments | K27: Debit | L27: 407.54 | M27: 0 | N27: -407.54 | O27: 67025.88 | P27: 0 | Q27: 0
A28: 27 | B28: 45702 | C28: 2025-02 | D28: 3 | E28: GOLD_BUSINESS_ACCOUNT_3.pdf | F28: 2 | G28: Int-BankingPmtFrmCu10141 | H28: Cu10141 | I28: Customer Receipts | J28: Sales Income | K28: Credit | L28: 0 | M28: 200 | N28: 200 | O28: 67225.88 | P28: 0 | Q28: 0
A29: 28 | B29: 45702 | C29: 2025-02 | D29: 3 | E29: GOLD_BUSINESS_ACCOUNT_3.pdf | F29: 2 | G29: Int-BankingPmtFrmCu10502 | H29: Cu10502 | I29: Customer Receipts | J29: Sales Income | K29: Credit | L29: 0 | M29: 300 | N29: 300 | O29: 67525.88 | P29: 0 | Q29: 0
A30: 29 | B30: 45702 | C30: 2025-02 | D30: 3 | E30: GOLD_BUSINESS_ACCOUNT_3.pdf | F30: 2 | G30: Int-BankingPmtFrmCu10141 | H30: Cu10141 | I30: Customer Receipts | J30: Sales Income | K30: Credit | L30: 0 | M30: 100 | N30: 100 | O30: 67625.88 | P30: 0 | Q30: 0
A31: 30 | B31: 45702 | C31: 2025-02 | D31: 3 | E31: GOLD_BUSINESS_ACCOUNT_3.pdf | F31: 2 | G31: Int-BankingPmtFrmCu10141 | H31: Cu10141 | I31: Customer Receipts | J31: Sales Income | K31: Credit | L31: 0 | M31: 200 | N31: 200 | O31: 67825.88 | P31: 0 | Q31: 0
A32: 31 | B32: 45702 | C32: 2025-02 | D32: 3 | E32: GOLD_BUSINESS_ACCOUNT_3.pdf | F32: 2 | G32: Int-BankingPmtFrmCu10587 | H32: Cu10587 | I32: Customer Receipts | J32: Sales Income | K32: Credit | L32: 0 | M32: 10000 | N32: 10000 | O32: 77825.88 | P32: 0 | Q32: 0
... A122: 121 | B122: 45716 | C122: 2025-02 | D122: 3 | E122: GOLD_BUSINESS_ACCOUNT_3.pdf | F122: 3 | G122: FNBOBPmtFNBOB000000033Cu1 Cu10745428 | H122: Cu1 | I122: Supplier / Payout Payments | J122: Cost of Sales / Supplier Payments | K122: Debit | L122: 5504.24 | M122: 0 | N122: -5504.24 | O122: 49484.24 | P122: 0 | Q122: 0
A123: 122 | B123: 45716 | C123: 2025-02 | D123: 3 | E123: GOLD_BUSINESS_ACCOUNT_3.pdf | F123: 3 | G123: ElectronicPaymentsBis/Int1OnTrueTiering 5.00 0.00 | I123: Other Income | J123: Other Income | K123: Credit | L123: 0 | M123: 49484.24 | N123: 49484.24 | O123: 5 | P123: 0 | Q123: 0 | R123: Review
A124: 123 | B124: 45716 | C124: 2025-02 | D124: 3 | E124: GOLD_BUSINESS_ACCOUNT_3.pdf | F124: 3 | G124: AccountFee | I124: Bank Charges | J124: Bank Fees | K124: Debit | L124: 89 | M124: 0 | N124: -89 | O124: 49395.24 | P124: 0.15 | Q124: 11.61
A125: 124 | B125: 45716 | C125: 2025-02 | D125: 3 | E125: GOLD_BUSINESS_ACCOUNT_3.pdf | F125: 3 | G125: Fees | I125: Other Payments | J125: General Expenses | K125: Debit | L125: 5 | M125: 0 | N125: -5 | O125: 49390.24 | P125: 0 | Q125: 0 | R125: Review
A126: 125 | B126: 45717 | C126: 2025-03 | D126: 4 | E126: GOLD_BUSINESS_ACCOUNT_4.pdf | F126: 1 | G126: Int-Banking Pmt Frm Cu11601 | H126: Cu11601 | I126: Customer Receipts | J126: Sales Income | K126: Credit | L126: 0 | M126: 500 | N126: 500 | O126: 49890.24 | P126: 0 | Q126: 0
A127: 126 | B127: 45717 | C127: 2025-03 | D127: 4 | E127: GOLD_BUSINESS_ACCOUNT_4.pdf | F127: 1 | G127: FNB OB Pmt FNB OB 000000045 Cu1 Cu11427 492 | H127: Cu1 | I127: Supplier / Payout Payments | J127: Cost of Sales / Supplier Payments | K127: Debit | L127: 440 | M127: 0 | N127: -440 | O127: 49450.24 | P127: 0 | Q127: 0
A128: 127 | B128: 45717 | C128: 2025-03 | D128: 4 | E128: GOLD_BUSINESS_ACCOUNT_4.pdf | F128: 1 | G128: FNB OB Pmt FNB OB 000000040 Cu1 Cu11470 480 | H128: Cu1 | I128: Supplier / Payout Payments | J128: Cost of Sales / Supplier Payments | K128: Debit | L128: 1182.26 | M128: 0 | N128: -1182.26 | O128: 48267.98 | P128: 0 | Q128: 0
A129: 128 | B129: 45717 | C129: 2025-03 | D129: 4 | E129: GOLD_BUSINESS_ACCOUNT_4.pdf | F129: 1 | G129: FNB OB Pmt FNB OB 000000042 Cu1 Cu10530 481 | H129: Cu1 | I129: Supplier / Payout Payments | J129: Cost of Sales / Supplier Payments | K129: Debit | L129: 1450 | M129: 0 | N129: -1450 | O129: 46817.98 | P129: 0 | Q129: 0
A130: 129 | B130: 45717 | C130: 2025-03 | D130: 4 | E130: GOLD_BUSINESS_ACCOUNT_4.pdf | F130: 1 | G130: FNB OB Pmt FNB OB 000000044 Cu1 Cu10607 487 | H130: Cu1 | I130: Supplier / Payout Payments | J130: Cost of Sales / Supplier Payments | K130: Debit | L130: 2064 | M130: 0 | N130: -2064 | O130: 44753.98 | P130: 0 | Q130: 0
A131: 130 | B131: 45717 | C131: 2025-03 | D131: 4 | E131: GOLD_BUSINESS_ACCOUNT_4.pdf | F131: 1 | G131: FNB OB Pmt FNB OB 000000043 Cu1 Cu10923 483 | H131: Cu1 | I131: Supplier / Payout Payments | J131: Cost of Sales / Supplier Payments | K131: Debit | L131: 4000 | M131: 0 | N131: -4000 | O131: 40753.98 | P131: 0 | Q131: 0
A132: 131 | B132: 45717 | C132: 2025-03 | D132: 4 | E132: GOLD_BUSINESS_ACCOUNT_4.pdf | F132: 1 | G132: FNB OB Pmt FNB OB 000000041 Cu1 Cu10348 488 | H132: Cu1 | I132: Supplier / Payout Payments | J132: Cost of Sales / Supplier Payments | K132: Debit | L132: 6360 | M132: 0 | N132: -6360 | O132: 34393.98 | P132: 0 | Q132: 0
A133: 132 | B133: 45717 | C133: 2025-03 | D133: 4 | E133: GOLD_BUSINESS_ACCOUNT_4.pdf | F133: 1 | G133: FNB OB Pmt FNB OB 000000039 Cu1 Cu11423 500 | H133: Cu1 | I133: Supplier / Payout Payments | J133: Cost of Sales / Supplier Payments | K133: Debit | L133: 20000 | M133: 0 | N133: -20000 | O133: 14393.98 | P133: 0 | Q133: 0
A134: 133 | B134: 45719 | C134: 2025-03 | D134: 4 | E134: GOLD_BUSINESS_ACCOUNT_4.pdf | F134: 1 | G134: Int-Banking Pmt Frm Cu11440 | H134: Cu11440 | I134: Customer Receipts | J134: Sales Income | K134: Credit | L134: 0 | M134: 170 | N134: 170 | O134: 14563.98 | P134: 0 | Q134: 0
A135: 134 | B135: 45719 | C135: 2025-03 | D135: 4 | E135: GOLD_BUSINESS_ACCOUNT_4.pdf | F135: 1 | G135: Int-Banking Pmt Frm Cu11585 | H135: Cu11585 | I135: Customer Receipts | J135: Sales Income | K135: Credit | L135: 0 | M135: 10000 | N135: 10000 | O135: 24563.98 | P135: 0 | Q135: 0
A136: 135 | B136: 45719 | C136: 2025-03 | D136: 4 | E136: GOLD_BUSINESS_ACCOUNT_4.pdf | F136: 1 | G136: Int-Banking Pmt Frm Cu11127 | H136: Cu11127 | I136: Customer Receipts | J136: Sales Income | K136: Credit | L136: 0 | M136: 100 | N136: 100 | O136: 24663.98 | P136: 0 | Q136: 0
A137: 136 | B137: 45719 | C137: 2025-03 | D137: 4 | E137: GOLD_BUSINESS_ACCOUNT_4.pdf | F137: 1 | G137: Int-Banking Pmt Frm Cu10745 | H137: Cu10745 | I137: Customer Receipts | J137: Sales Income | K137: Credit | L137: 0 | M137: 10000 | N137: 10000 | O137: 34663.98 | P137: 0 | Q137: 0
... A185: 184 | B185: 45721 | C185: 2025-03 | D185: 4 | E185: GOLD_BUSINESS_ACCOUNT_4.pdf | F185: 2 | G185: Int-Banking Pmt Frm Cu11585 | H185: Cu11585 | I185: Customer Receipts | J185: Sales Income | K185: Credit | L185: 0 | M185: 25000 | N185: 25000 | O185: 75929.29 | P185: 0 | Q185: 0
A186: 185 | B186: 45722 | C186: 2025-03 | D186: 4 | E186: GOLD_BUSINESS_ACCOUNT_4.pdf | F186: 2 | G186: FNB OB Trf FNB OB Trf 000000066 Luxe Internal | I186: Internal Transfers | J186: Transfers | K186: Debit | L186: 20000 | M186: 0 | N186: -20000 | O186: 55929.29 | P186: 0 | Q186: 0
A187: 186 | B187: 45722 | C187: 2025-03 | D187: 4 | E187: GOLD_BUSINESS_ACCOUNT_4.pdf | F187: 2 | G187: FNB OB Pmt FNB OB 000000067 Cu1 Cu11767 701 | H187: Cu1 | I187: Supplier / Payout Payments | J187: Cost of Sales / Supplier Payments | K187: Debit | L187: 2587 | M187: 0 | N187: -2587 | O187: 53342.29 | P187: 0 | Q187: 0
A188: 187 | B188: 45722 | C188: 2025-03 | D188: 4 | E188: GOLD_BUSINESS_ACCOUNT_4.pdf | F188: 2 | G188: FNB OB Pmt FNB OB 000000068 Cu1 Cu10745 733 | H188: Cu1 | I188: Supplier / Payout Payments | J188: Cost of Sales / Supplier Payments | K188: Debit | L188: 108 | M188: 0 | N188: -108 | O188: 53234.29 | P188: 0 | Q188: 0
A189: 188 | B189: 45722 | C189: 2025-03 | D189: 4 | E189: GOLD_BUSINESS_ACCOUNT_4.pdf | F189: 2 | G189: Int-Banking Pmt Frm Cu11767 | H189: Cu11767 | I189: Customer Receipts | J189: Sales Income | K189: Credit | L189: 0 | M189: 500 | N189: 500 | O189: 53734.29 | P189: 0 | Q189: 0
A190: 189 | B190: 45722 | C190: 2025-03 | D190: 4 | E190: GOLD_BUSINESS_ACCOUNT_4.pdf | F190: 2 | G190: Int-Banking Pmt Frm Cu12042 | H190: Cu12042 | I190: Customer Receipts | J190: Sales Income | K190: Credit | L190: 0 | M190: 100 | N190: 100 | O190: 53834.29 | P190: 0 | Q190: 0
A191: 190 | B191: 45722 | C191: 2025-03 | D191: 4 | E191: GOLD_BUSINESS_ACCOUNT_4.pdf | F191: 2 | G191: Int-Banking Pmt Frm Cu11741 | H191: Cu11741 | I191: Customer Receipts | J191: Sales Income | K191: Credit | L191: 0 | M191: 1000 | N191: 1000 | O191: 54834.29 | P191: 0 | Q191: 0
A192: 191 | B192: 45722 | C192: 2025-03 | D192: 4 | E192: GOLD_BUSINESS_ACCOUNT_4.pdf | F192: 2 | G192: Int-Banking Pmt Frm Cu10477 | H192: Cu10477 | I192: Customer Receipts | J192: Sales Income | K192: Credit | L192: 0 | M192: 300 | N192: 300 | O192: 55134.29 | P192: 0 | Q192: 0
A193: 192 | B193: 45722 | C193: 2025-03 | D193: 4 | E193: GOLD_BUSINESS_ACCOUNT_4.pdf | F193: 2 | G193: Int-Banking Pmt Frm Cu10348 | H193: Cu10348 | I193: Customer Receipts | J193: Sales Income | K193: Credit | L193: 0 | M193: 3000 | N193: 3000 | O193: 58134.29 | P193: 0 | Q193: 0
A194: 193 | B194: 45722 | C194: 2025-03 | D194: 4 | E194: GOLD_BUSINESS_ACCOUNT_4.pdf | F194: 2 | G194: Int-Banking Pmt Frm Cu12132 | H194: Cu12132 | I194: Customer Receipts | J194: Sales Income | K194: Credit | L194: 0 | M194: 200 | N194: 200 | O194: 58334.29 | P194: 0 | Q194: 0
A195: 194 | B195: 45722 | C195: 2025-03 | D195: 4 | E195: GOLD_BUSINESS_ACCOUNT_4.pdf | F195: 2 | G195: Int-Banking Pmt Frm Cu11585 | H195: Cu11585 | I195: Customer Receipts | J195: Sales Income | K195: Credit | L195: 0 | M195: 5000 | N195: 5000 | O195: 63334.29 | P195: 0 | Q195: 0
A196: 195 | B196: 45722 | C196: 2025-03 | D196: 4 | E196: GOLD_BUSINESS_ACCOUNT_4.pdf | F196: 2 | G196: Int-Banking Pmt Frm Cu11585 | H196: Cu11585 | I196: Customer Receipts | J196: Sales Income | K196: Credit | L196: 0 | M196: 5000 | N196: 5000 | O196: 68334.29 | P196: 0 | Q196: 0
A197: 196 | B197: 45722 | C197: 2025-03 | D197: 4 | E197: GOLD_BUSINESS_ACCOUNT_4.pdf | F197: 2 | G197: Int-Banking Pmt Frm Cu10530 | H197: Cu10530 | I197: Customer Receipts | J197: Sales Income | K197: Credit | L197: 0 | M197: 600 | N197: 600 | O197: 68934.29 | P197: 0 | Q197: 0
A198: 197 | B198: 45722 | C198: 2025-03 | D198: 4 | E198: GOLD_BUSINESS_ACCOUNT_4.pdf | F198: 2 | G198: Int-Banking Pmt Frm Cu11585 | H198: Cu11585 | I198: Customer Receipts | J198: Sales Income | K198: Credit | L198: 0 | M198: 10000 | N198: 10000 | O198: 78934.29 | P198: 0 | Q198: 0
... A213: 212 | B213: 45723 | C213: 2025-03 | D213: 4 | E213: GOLD_BUSINESS_ACCOUNT_4.pdf | F213: 3 | G213: Int-Banking Pmt Frm Cu11296 | H213: Cu11296 | I213: Customer Receipts | J213: Sales Income | K213: Credit | L213: 0 | M213: 500 | N213: 500 | O213: 95278.88 | P213: 0 | Q213: 0
A214: 213 | B214: 45723 | C214: 2025-03 | D214: 4 | E214: GOLD_BUSINESS_ACCOUNT_4.pdf | F214: 3 | G214: FNB OB Trf FNB OB Trf 000000074 Internal Transfer | I214: Internal Transfers | J214: Transfers | K214: Debit | L214: 10000 | M214: 0 | N214: -10000 | O214: 85278.88 | P214: 0 | Q214: 0
A215: 214 | B215: 45723 | C215: 2025-03 | D215: 4 | E215: GOLD_BUSINESS_ACCOUNT_4.pdf | F215: 3 | G215: Int-Banking Pmt Frm Cu10530 | H215: Cu10530 | I215: Customer Receipts | J215: Sales Income | K215: Credit | L215: 0 | M215: 1000 | N215: 1000 | O215: 86278.88 | P215: 0 | Q215: 0
A216: 215 | B216: 45723 | C216: 2025-03 | D216: 4 | E216: GOLD_BUSINESS_ACCOUNT_4.pdf | F216: 3 | G216: Int-Banking Pmt Frm Cu10348 | H216: Cu10348 | I216: Customer Receipts | J216: Sales Income | K216: Credit | L216: 0 | M216: 6000 | N216: 6000 | O216: 92278.88 | P216: 0 | Q216: 0
A217: 216 | B217: 45723 | C217: 2025-03 | D217: 4 | E217: GOLD_BUSINESS_ACCOUNT_4.pdf | F217: 3 | G217: Int-Banking Pmt Frm Cu12199 | H217: Cu12199 | I217: Customer Receipts | J217: Sales Income | K217: Credit | L217: 0 | M217: 3000 | N217: 3000 | O217: 95278.88 | P217: 0 | Q217: 0
A218: 217 | B218: 45723 | C218: 2025-03 | D218: 4 | E218: GOLD_BUSINESS_ACCOUNT_4.pdf | F218: 3 | G218: Int-Banking Pmt Frm Cu11832 | H218: Cu11832 | I218: Customer Receipts | J218: Sales Income | K218: Credit | L218: 0 | M218: 2000 | N218: 2000 | O218: 97278.88 | P218: 0 | Q218: 0
A219: 218 | B219: 45723 | C219: 2025-03 | D219: 4 | E219: GOLD_BUSINESS_ACCOUNT_4.pdf | F219: 3 | G219: Int-Banking Pmt Frm Cu12224 | H219: Cu12224 | I219: Customer Receipts | J219: Sales Income | K219: Credit | L219: 0 | M219: 3000 | N219: 3000 | O219: 100278.88 | P219: 0 | Q219: 0
A220: 219 | B220: 45723 | C220: 2025-03 | D220: 4 | E220: GOLD_BUSINESS_ACCOUNT_4.pdf | F220: 3 | G220: Int-Banking Pmt Frm Cu12153 | H220: Cu12153 | I220: Customer Receipts | J220: Sales Income | K220: Credit | L220: 0 | M220: 100 | N220: 100 | O220: 100378.88 | P220: 0 | Q220: 0
A221: 220 | B221: 45723 | C221: 2025-03 | D221: 4 | E221: GOLD_BUSINESS_ACCOUNT_4.pdf | F221: 3 | G221: Int-Banking Pmt Frm Cu10473 | H221: Cu10473 | I221: Customer Receipts | J221: Sales Income | K221: Credit | L221: 0 | M221: 2000 | N221: 2000 | O221: 102378.88 | P221: 0 | Q221: 0
A222: 221 | B222: 45723 | C222: 2025-03 | D222: 4 | E222: GOLD_BUSINESS_ACCOUNT_4.pdf | F222: 3 | G222: Int-Banking Pmt Frm Cu10224 | H222: Cu10224 | I222: Customer Receipts | J222: Sales Income | K222: Credit | L222: 0 | M222: 150 | N222: 150 | O222: 102528.88 | P222: 0 | Q222: 0
A223: 222 | B223: 45723 | C223: 2025-03 | D223: 4 | E223: GOLD_BUSINESS_ACCOUNT_4.pdf | F223: 3 | G223: Int-Banking Pmt Frm Cu11832 | H223: Cu11832 | I223: Customer Receipts | J223: Sales Income | K223: Credit | L223: 0 | M223: 1000 | N223: 1000 | O223: 103528.88 | P223: 0 | Q223: 0
A224: 223 | B224: 45723 | C224: 2025-03 | D224: 4 | E224: GOLD_BUSINESS_ACCOUNT_4.pdf | F224: 3 | G224: Int-Banking Pmt Frm Cu12031 | H224: Cu12031 | I224: Customer Receipts | J224: Sales Income | K224: Credit | L224: 0 | M224: 225 | N224: 225 | O224: 103753.88 | P224: 0 | Q224: 0
A225: 224 | B225: 45723 | C225: 2025-03 | D225: 4 | E225: GOLD_BUSINESS_ACCOUNT_4.pdf | F225: 3 | G225: Int-Banking Pmt Frm Cu10355 | H225: Cu10355 | I225: Customer Receipts | J225: Sales Income | K225: Credit | L225: 0 | M225: 400 | N225: 400 | O225: 104153.88 | P225: 0 | Q225: 0
A226: 225 | B226: 45723 | C226: 2025-03 | D226: 4 | E226: GOLD_BUSINESS_ACCOUNT_4.pdf | F226: 3 | G226: FNB OB Trf FNB OB Trf 000000075 Internal Transfer | I226: Internal Transfers | J226: Transfers | K226: Debit | L226: 3000 | M226: 0 | N226: -3000 | O226: 101153.88 | P226: 0 | Q226: 0
A227: 226 | B227: 45723 | C227: 2025-03 | D227: 4 | E227: GOLD_BUSINESS_ACCOUNT_4.pdf | F227: 3 | G227: FNB OB Pmt FNB OB 000000076 Cu1 Cu11767 806 | H227: Cu1 | I227: Supplier / Payout Payments | J227: Cost of Sales / Supplier Payments | K227: Debit | L227: 531 | M227: 0 | N227: -531 | O227: 100622.88 | P227: 0 | Q227: 0
A228: 227 | B228: 45723 | C228: 2025-03 | D228: 4 | E228: GOLD_BUSINESS_ACCOUNT_4.pdf | F228: 3 | G228: FNB OB Pmt FNB OB 000000077 Cu1 Cu10745 810 | H228: Cu1 | I228: Supplier / Payout Payments | J228: Cost of Sales / Supplier Payments | K228: Debit | L228: 10844 | M228: 0 | N228: -10844 | O228: 89778.88 | P228: 0 | Q228: 0
A229: 228 | B229: 45723 | C229: 2025-03 | D229: 4 | E229: GOLD_BUSINESS_ACCOUNT_4.pdf | F229: 3 | G229: FNB OB Pmt FNB OB 000000078 Cu1 Cu11002 804 | H229: Cu1 | I229: Supplier / Payout Payments | J229: Cost of Sales / Supplier Payments | K229: Debit | L229: 17304.32 | M229: 0 | N229: -17304.32 | O229: 72474.56 | P229: 0 | Q229: 0
A230: 229 | B230: 45723 | C230: 2025-03 | D230: 4 | E230: GOLD_BUSINESS_ACCOUNT_4.pdf | F230: 3 | G230: Int-Banking Pmt Frm Cu11741 | H230: Cu11741 | I230: Customer Receipts | J230: Sales Income | K230: Credit | L230: 0 | M230: 1500 | N230: 1500 | O230: 73974.56 | P230: 0 | Q230: 0
A231: 230 | B231: 45723 | C231: 2025-03 | D231: 4 | E231: GOLD_BUSINESS_ACCOUNT_4.pdf | F231: 3 | G231: Int-Banking Pmt Frm Cu12258 | H231: Cu12258 | I231: Customer Receipts | J231: Sales Income | K231: Credit | L231: 0 | M231: 500 | N231: 500 | O231: 74474.56 | P231: 0 | Q231: 0
A232: 231 | B232: 45723 | C232: 2025-03 | D232: 4 | E232: GOLD_BUSINESS_ACCOUNT_4.pdf | F232: 3 | G232: FNB OB Pmt FNB OB 000000079 Cu1 Cu10745 831 | H232: Cu1 | I232: Supplier / Payout Payments | J232: Cost of Sales / Supplier Payments | K232: Debit | L232: 3171.91 | M232: 0 | N232: -3171.91 | O232: 71302.65 | P232: 0 | Q232: 0
A233: 232 | B233: 45723 | C233: 2025-03 | D233: 4 | E233: GOLD_BUSINESS_ACCOUNT_4.pdf | F233: 3 | G233: FNB OB Pmt FNB OB 000000080 Cu1 Cu10348 836 | H233: Cu1 | I233: Supplier / Payout Payments | J233: Cost of Sales / Supplier Payments | K233: Debit | L233: 16200 | M233: 0 | N233: -16200 | O233: 55102.65 | P233: 0 | Q233: 0
A234: 233 | B234: 45723 | C234: 2025-03 | D234: 4 | E234: GOLD_BUSINESS_ACCOUNT_4.pdf | F234: 3 | G234: FNB OB Pmt FNB OB 000000081 Cu1 Cu11767 825 | H234: Cu1 | I234: Supplier / Payout Payments | J234: Cost of Sales / Supplier Payments | K234: Debit | L234: 5978 | M234: 0 | N234: -5978 | O234: 49124.65 | P234: 0 | Q234: 0
A235: 234 | B235: 45723 | C235: 2025-03 | D235: 4 | E235: GOLD_BUSINESS_ACCOUNT_4.pdf | F235: 3 | G235: Int-Banking Pmt Frm Cu11538 | H235: Cu11538 | I235: Customer Receipts | J235: Sales Income | K235: Credit | L235: 0 | M235: 1000 | N235: 1000 | O235: 50124.65 | P235: 0 | Q235: 0
A236: 235 | B236: 45723 | C236: 2025-03 | D236: 4 | E236: GOLD_BUSINESS_ACCOUNT_4.pdf | F236: 3 | G236: Int-Banking Pmt Frm Cu10348 | H236: Cu10348 | I236: Customer Receipts | J236: Sales Income | K236: Credit | L236: 0 | M236: 1000 | N236: 1000 | O236: 51124.65 | P236: 0 | Q236: 0
A237: 236 | B237: 45723 | C237: 2025-03 | D237: 4 | E237: GOLD_BUSINESS_ACCOUNT_4.pdf | F237: 3 | G237: FNB OB Pmt FNB OB 000000069 Cu1 Cu11767 756 | H237: Cu1 | I237: Supplier / Payout Payments | J237: Cost of Sales / Supplier Payments | K237: Debit | L237: 3352 | M237: 0 | N237: -3352 | O237: 47772.65 | P237: 0 | Q237: 0
A238: 237 | B238: 45723 | C238: 2025-03 | D238: 4 | E238: GOLD_BUSINESS_ACCOUNT_4.pdf | F238: 3 | G238: FNB OB Pmt FNB OB 000000070 Cu1 Cu10530 759 | H238: Cu1 | I238: Supplier / Payout Payments | J238: Cost of Sales / Supplier Payments | K238: Debit | L238: 4310 | M238: 0 | N238: -4310 | O238: 43462.65 | P238: 0 | Q238: 0
... A311: 310 | B311: 45729 | C311: 2025-03 | D311: 4 | E311: GOLD_BUSINESS_ACCOUNT_4.pdf | F311: 4 | G311: Int-Banking Pmt Frm Cu11601 | H311: Cu11601 | I311: Customer Receipts | J311: Sales Income | K311: Credit | L311: 0 | M311: 3000 | N311: 3000 | O311: 87621.48 | P311: 0 | Q311: 0
A312: 311 | B312: 45729 | C312: 2025-03 | D312: 4 | E312: GOLD_BUSINESS_ACCOUNT_4.pdf | F312: 4 | G312: FNB OB Trf FNB OB Trf 000000103 Inv13032025 | I312: Internal Transfers | J312: Transfers | K312: Debit | L312: 37000 | M312: 0 | N312: -37000 | O312: 50621.48 | P312: 0 | Q312: 0
A313: 312 | B313: 45729 | C313: 2025-03 | D313: 4 | E313: GOLD_BUSINESS_ACCOUNT_4.pdf | F313: 4 | G313: Int-Banking Pmt Frm Cu10833 | H313: Cu10833 | I313: Customer Receipts | J313: Sales Income | K313: Credit | L313: 0 | M313: 250 | N313: 250 | O313: 50871.48 | P313: 0 | Q313: 0
A314: 313 | B314: 45729 | C314: 2025-03 | D314: 4 | E314: GOLD_BUSINESS_ACCOUNT_4.pdf | F314: 4 | G314: Int-Banking Pmt Frm Cu12183 | H314: Cu12183 | I314: Customer Receipts | J314: Sales Income | K314: Credit | L314: 0 | M314: 3000 | N314: 3000 | O314: 53871.48 | P314: 0 | Q314: 0
A315: 314 | B315: 45729 | C315: 2025-03 | D315: 4 | E315: GOLD_BUSINESS_ACCOUNT_4.pdf | F315: 4 | G315: FNB OB Pmt FNB OB 000000104 Cu1 Cu11466 1295 | H315: Cu1 | I315: Supplier / Payout Payments | J315: Cost of Sales / Supplier Payments | K315: Debit | L315: 1900 | M315: 0 | N315: -1900 | O315: 51971.48 | P315: 0 | Q315: 0
A316: 315 | B316: 45729 | C316: 2025-03 | D316: 4 | E316: GOLD_BUSINESS_ACCOUNT_4.pdf | F316: 4 | G316: FNB OB Pmt FNB OB 000000105 Cu1 Cu10592 1320 | H316: Cu1 | I316: Supplier / Payout Payments | J316: Cost of Sales / Supplier Payments | K316: Debit | L316: 2000 | M316: 0 | N316: -2000 | O316: 49971.48 | P316: 0 | Q316: 0
A317: 316 | B317: 45729 | C317: 2025-03 | D317: 4 | E317: GOLD_BUSINESS_ACCOUNT_4.pdf | F317: 4 | G317: FNB OB Pmt FNB OB 000000106 Cu1 Cu10477 1419 | H317: Cu1 | I317: Supplier / Payout Payments | J317: Cost of Sales / Supplier Payments | K317: Debit | L317: 5000 | M317: 0 | N317: -5000 | O317: 44971.48 | P317: 0 | Q317: 0
A318: 317 | B318: 45729 | C318: 2025-03 | D318: 4 | E318: GOLD_BUSINESS_ACCOUNT_4.pdf | F318: 4 | G318: FNB OB Pmt FNB OB 000000107 Cu1 Cu12597 1423 | H318: Cu1 | I318: Supplier / Payout Payments | J318: Cost of Sales / Supplier Payments | K318: Debit | L318: 260 | M318: 0 | N318: -260 | O318: 44711.48 | P318: 0 | Q318: 0
A319: 318 | B319: 45729 | C319: 2025-03 | D319: 4 | E319: GOLD_BUSINESS_ACCOUNT_4.pdf | F319: 4 | G319: FNB OB Pmt FNB OB 000000108 Cu1 Cu10258 1429 | H319: Cu1 | I319: Supplier / Payout Payments | J319: Cost of Sales / Supplier Payments | K319: Debit | L319: 7000 | M319: 0 | N319: -7000 | O319: 37711.48 | P319: 0 | Q319: 0
A320: 319 | B320: 45729 | C320: 2025-03 | D320: 4 | E320: GOLD_BUSINESS_ACCOUNT_4.pdf | F320: 4 | G320: Int-Banking Pmt Frm Cu12224 | H320: Cu12224 | I320: Customer Receipts | J320: Sales Income | K320: Credit | L320: 0 | M320: 3000 | N320: 3000 | O320: 40711.48 | P320: 0 | Q320: 0
A321: 320 | B321: 45729 | C321: 2025-03 | D321: 4 | E321: GOLD_BUSINESS_ACCOUNT_4.pdf | F321: 5 | G321: Int-Banking Pmt Frm Cu11852 | H321: Cu11852 | I321: Customer Receipts | J321: Sales Income | K321: Credit | L321: 0 | M321: 100 | N321: 100 | O321: 40811.48 | P321: 0 | Q321: 0
A322: 321 | B322: 45729 | C322: 2025-03 | D322: 4 | E322: GOLD_BUSINESS_ACCOUNT_4.pdf | F322: 5 | G322: Int-Banking Pmt Frm Cu10355 | H322: Cu10355 | I322: Customer Receipts | J322: Sales Income | K322: Credit | L322: 0 | M322: 200 | N322: 200 | O322: 41011.48 | P322: 0 | Q322: 0
...

Sheet Monthly Summary
A1: Month | B1: Debits | C1: Credits | D1: Net Movement | E1: Transaction Count | F1: Bank Charges | G1: VAT on Bank Charges | H1: Customer Receipts | I1: Supplier Payments
A2: 2025-01 | B2: =SUMIFS(Transactions!$L:$L,Transactions!$C:$C,A2) -> 89 | C2: =SUMIFS(Transactions!$M:$M,Transactions!$C:$C,A2) -> 0 | D2: =C2-B2 -> -89 | E2: =COUNTIFS(Transactions!$C:$C,A2) -> 1 | F2: =SUMIFS(Transactions!$L:$L,Transactions!$C:$C,A2,Transactions!$I:$I,"Bank Charges") -> 89 | G2: =SUMIFS(Transactions!$Q:$Q,Transactions!$C:$C,A2) -> 11.61 | H2: =SUMIFS(Transactions!$M:$M,Transactions!$C:$C,A2,Transactions!$I:$I,"Customer Receipts")+SUMIFS(Transactions!$M:$M,Transactions!$C:$C,A2,Transactions!$I:$I,"Card / Payment Gateway Receipts") -> 0 | I2: =SUMIFS(Transactions!$L:$L,Transactions!$C:$C,A2,Transactions!$I:$I,"Supplier / Payout Payments") -> 0
A3: 2025-02 | B3: =SUMIFS(Transactions!$L:$L,Transactions!$C:$C,A3) -> 290914.58 | C3: =SUMIFS(Transactions!$M:$M,Transactions!$C:$C,A3) -> 388949.24 | D3: =C3-B3 -> 98034.66 | E3: =COUNTIFS(Transactions!$C:$C,A3) -> 123 | F3: =SUMIFS(Transactions!$L:$L,Transactions!$C:$C,A3,Transactions!$I:$I,"Bank Charges") -> 89 | G3: =SUMIFS(Transactions!$Q:$Q,Transactions!$C:$C,A3) -> 11.61 | H3: =SUMIFS(Transactions!$M:$M,Transactions!$C:$C,A3,Transactions!$I:$I,"Customer Receipts")+SUMIFS(Transactions!$M:$M,Transactions!$C:$C,A3,Transactions!$I:$I,"Card / Payment Gateway Receipts") -> 239465 | I3: =SUMIFS(Transactions!$L:$L,Transactions!$C:$C,A3,Transactions!$I:$I,"Supplier / Payout Payments") -> 290720.58
A4: 2025-03 | B4: =SUMIFS(Transactions!$L:$L,Transactions!$C:$C,A4) -> 919668.21 | C4: =SUMIFS(Transactions!$M:$M,Transactions!$C:$C,A4) -> 923115 | D4: =C4-B4 -> 3446.79 | E4: =COUNTIFS(Transactions!$C:$C,A4) -> 508 | F4: =SUMIFS(Transactions!$L:$L,Transactions!$C:$C,A4,Transactions!$I:$I,"Bank Charges") -> 139 | G4: =SUMIFS(Transactions!$Q:$Q,Transactions!$C:$C,A4) -> 18.13 | H4: =SUMIFS(Transactions!$M:$M,Transactions!$C:$C,A4,Transactions!$I:$I,"Customer Receipts")+SUMIFS(Transactions!$M:$M,Transactions!$C:$C,A4,Transactions!$I:$I,"Card / Payment Gateway Receipts") -> 623115 | I4: =SUMIFS(Transactions!$L:$L,Transactions!$C:$C,A4,Transactions!$I:$I,"Supplier / Payout Payments") -> 836657.21
A5: 2025-04 | B5: =SUMIFS(Transactions!$L:$L,Transactions!$C:$C,A5) -> 513921.38 | C5: =SUMIFS(Transactions!$M:$M,Transactions!$C:$C,A5) -> 504908.94 | D5: =C5-B5 -> -9012.44 | E5: =COUNTIFS(Transactions!$C:$C,A5) -> 474 | F5: =SUMIFS(Transactions!$L:$L,Transactions!$C:$C,A5,Transactions!$I:$I,"Bank Charges") -> 579 | G5: =SUMIFS(Transactions!$Q:$Q,Transactions!$C:$C,A5) -> 75.48 | H5: =SUMIFS(Transactions!$M:$M,Transactions!$C:$C,A5,Transactions!$I:$I,"Customer Receipts")+SUMIFS(Transactions!$M:$M,Transactions!$C:$C,A5,Transactions!$I:$I,"Card / Payment Gateway Receipts") -> 500746 | I5: =SUMIFS(Transactions!$L:$L,Transactions!$C:$C,A5,Transactions!$I:$I,"Supplier / Payout Payments") -> 489456.58
A6: 2025-05 | B6: =SUMIFS(Transactions!$L:$L,Transactions!$C:$C,A6) -> 428038.5 | C6: =SUMIFS(Transactions!$M:$M,Transactions!$C:$C,A6) -> 437864 | D6: =C6-B6 -> 9825.5 | E6: =COUNTIFS(Transactions!$C:$C,A6) -> 496 | F6: =SUMIFS(Transactions!$L:$L,Transactions!$C:$C,A6,Transactions!$I:$I,"Bank Charges") -> 100 | G6: =SUMIFS(Transactions!$Q:$Q,Transactions!$C:$C,A6) -> 13.04 | H6: =SUMIFS(Transactions!$M:$M,Transactions!$C:$C,A6,Transactions!$I:$I,"Customer Receipts")+SUMIFS(Transactions!$M:$M,Transactions!$C:$C,A6,Transactions!$I:$I,"Card / Payment Gateway Receipts") -> 437864 | I6: =SUMIFS(Transactions!$L:$L,Transactions!$C:$C,A6,Transactions!$I:$I,"Supplier / Payout Payments") -> 328228.42
A7: 2025-08 | B7: =SUMIFS(Transactions!$L:$L,Transactions!$C:$C,A7) -> 1883515 | C7: =SUMIFS(Transactions!$M:$M,Transactions!$C:$C,A7) -> 1833061.2 | D7: =C7-B7 -> -50453.82 | E7: =COUNTIFS(Transactions!$C:$C,A7) -> 1050 | F7: =SUMIFS(Transactions!$L:$L,Transactions!$C:$C,A7,Transactions!$I:$I,"Bank Charges") -> 843 | G7: =SUMIFS(Transactions!$Q:$Q,Transactions!$C:$C,A7) -> 110 | H7: =SUMIFS(Transactions!$M:$M,Transactions!$C:$C,A7,Transactions!$I:$I,"Customer Receipts")+SUMIFS(Transactions!$M:$M,Transactions!$C:$C,A7,Transactions!$I:$I,"Card / Payment Gateway Receipts") -> 1581082.2 | I7: =SUMIFS(Transactions!$L:$L,Transactions!$C:$C,A7,Transactions!$I:$I,"Supplier / Payout Payments") -> 1341531.2

Sheet Profit & Loss
A1: Category | B1: GL Account | C1: Total Debit | D1: Total Credit | E1: Net | F1: Review Required
A2: Bank Charges | B2: Bank Fees | C2: =SUMIFS(Transactions!$L:$L,Transactions!$I:$I,A2) -> 1839 | D2: =SUMIFS(Transactions!$M:$M,Transactions!$I:$I,A2) -> 0 | E2: =D2-C2 -> -1839 | F2: =IF(OR(A2="Other Income",A2="Other Payments"),"Yes","")
A3: Card / Payment Gateway Receipts | B3: Sales Income | C3: =SUMIFS(Transactions!$L:$L,Transactions!$I:$I,A3) -> 0 | D3: =SUMIFS(Transactions!$M:$M,Transactions!$I:$I,A3) -> 886200.57 | E3: =D3-C3 -> 886200.57 | F3: =IF(OR(A3="Other Income",A3="Other Payments"),"Yes","")
A4: Customer Receipts | B4: Sales Income | C4: =SUMIFS(Transactions!$L:$L,Transactions!$I:$I,A4) -> 0 | D4: =SUMIFS(Transactions!$M:$M,Transactions!$I:$I,A4) -> 2496071.6 | E4: =D4-C4 -> 2496071.6 | F4: =IF(OR(A4="Other Income",A4="Other Payments"),"Yes","")
A5: Internal Transfers | B5: Transfers | C5: =SUMIFS(Transactions!$L:$L,Transactions!$I:$I,A5) -> 696000 | D5: =SUMIFS(Transactions!$M:$M,Transactions!$I:$I,A5) -> 470000 | E5: =D5-C5 -> -226000 | F5: =IF(OR(A5="Other Income",A5="Other Payments"),"Yes","")
A6: International Payments | B6: Foreign Payments | C6: =SUMIFS(Transactions!$L:$L,Transactions!$I:$I,A6) -> 51438.74 | D6: =SUMIFS(Transactions!$M:$M,Transactions!$I:$I,A6) -> 0 | E6: =D6-C6 -> -51438.74 | F6: =IF(OR(A6="Other Income",A6="Other Payments"),"Yes","")
A7: Online Payments | B7: Online Payments | C7: =SUMIFS(Transactions!$L:$L,Transactions!$I:$I,A7) -> 100 | D7: =SUMIFS(Transactions!$M:$M,Transactions!$I:$I,A7) -> 0 | E7: =D7-C7 -> -100 | F7: =IF(OR(A7="Other Income",A7="Other Payments"),"Yes","")
A8: Other Income | B8: Other Income | C8: =SUMIFS(Transactions!$L:$L,Transactions!$I:$I,A8) -> 0 | D8: =SUMIFS(Transactions!$M:$M,Transactions!$I:$I,A8) -> 235626.18 | E8: =D8-C8 -> 235626.18 | F8: =IF(OR(A8="Other Income",A8="Other Payments"),"Yes","") -> Yes
A9: Other Payments | B9: General Expenses | C9: =SUMIFS(Transactions!$L:$L,Transactions!$I:$I,A9) -> 175 | D9: =SUMIFS(Transactions!$M:$M,Transactions!$I:$I,A9) -> 0 | E9: =D9-C9 -> -175 | F9: =IF(OR(A9="Other Income",A9="Other Payments"),"Yes","") -> Yes
A10: Supplier / Payout Payments | B10: Cost of Sales / Supplier Payments | C10: =SUMIFS(Transactions!$L:$L,Transactions!$I:$I,A10) -> 3286593.9 | D10: =SUMIFS(Transactions!$M:$M,Transactions!$I:$I,A10) -> 0 | E10: =D10-C10 -> -3286593.9 | F10: =IF(OR(A10="Other Income",A10="Other Payments"),"Yes","")

Sheet Reconciliation
A1: Bank Reconciliation
A2: Total credits extracted | B2: =SUM(Transactions!M:M) -> 4087898.4
A3: Total debits extracted | B3: =SUM(Transactions!L:L) -> 4036146.7
A4: Net movement | B4: =B2-B3 -> 51751.69
A5: Opening balance (first provided statement) | B5: =_xludf.MINIFS('Source Statements'!C:C,'Source Statements'!C:C,">0") -> #NAME?
A6: Closing balance (last provided statement) | B6: =INDEX('Source Statements'!D:D,MATCH(MAX('Source Statements'!B:B),'Source Statements'!B:B,0)) -> #N/A
A7: Calculated closing balance | B7: =B5+B4 -> #NAME?
A8: Difference | B8: =B6-B7 -> #N/A
A9: Review notes | B9: Difference will not be zero if statement months are missing between uploaded PDFs.

Sheet Category Rules
A1: Category | B1: GL Account | C1: Rule / Source Pattern | D1: Treatment
A2: Customer Receipts | B2: Sales Income | C2: Int-Banking Pmt Frm / Magtape Credit / Payment Cr | D2: Credit / income received
A3: Card / Payment Gateway Receipts | B3: Sales Income | C3: Netcash / Zapper / Flash Mobile | D3: Credit / sales receipts via payment processor
A4: Supplier / Payout Payments | B4: Cost of Sales / Supplier Payments | C4: FNB OB Pmt | D4: Debit / supplier or customer payouts
A5: Internal Transfers | B5: Transfers | C5: FNB OB Trf | D5: Debit/Credit transfer between accounts
A6: Bank Charges | B6: Bank Fees | C6: Account Fee / bank transaction fee / forex fee | D6: Debit / bank charges, VAT extracted where applicable
A7: International Payments | B7: Foreign Payments | C7: Outward Swift | D7: Debit / international or forex-related payment
A8: Online Payments | B8: Online Payments | C8: Internet Pmt To | D8: Debit / online payment
A9: Other Income | B9: Other Income | C9: Unmatched credit | D9: Needs accountant review
A10: Other Payments | B10: General Expenses | C10: Unmatched debit | D10: Needs accountant review

Sheet Source Statements
A1: Source File | B1: Statement No | C1: Opening Balance | D1: Closing Balance | E1: Rows Extracted | F1: First Tx Date | G1: Last Tx Date
A2: GOLD_BUSINESS_ACCOUNT_2.pdf | B2: 2 | C2: 928.82 | D2: 839.82 | E2: 1 | F2: 2025-01-31 | G2: 2025-01-31
A3: GOLD_BUSINESS_ACCOUNT_3.pdf | B3: 3 | C3: 839.82 | D3: 49390.24 | E3: 123 | F3: 2025-02-03 | G3: 2025-02-28
A4: GOLD_BUSINESS_ACCOUNT_4.pdf | B4: 4 | C4: 49390.24 | D4: 52837.03 | E4: 508 | F4: 2025-03-01 | G4: 2025-03-31
A5: GOLD_BUSINESS_ACCOUNT_5.pdf | B5: 5 | C5: 52837.03 | D5: 43824.59 | E5: 474 | F5: 2025-04-01 | G5: 2025-04-30
A6: GOLD_BUSINESS_ACCOUNT_6.pdf | B6: 6 | C6: 43824.59 | D6: 48737.34 | E6: 496 | F6: 2025-05-02 | G6: 2025-05-15
A7: GOLD BUSINESS ACCOUNT 10.pdf | B7: 10 | C7: 50682.69 | D7: 228.87 | E7: 1050 | F7: 2025-08-01 | G7: 2025-08-31
